BetterPyUnitFormat/BetterPyUnitResult.py
BetterPyUnitFormat/BetterPyUnitTestRunner.py
BetterPyUnitFormat/__init__.py
Better_PyUnit_Format-0.2.3.dist-info/LICENSE
Better_PyUnit_Format-0.2.3.dist-info/METADATA
Better_PyUnit_Format-0.2.3.dist-info/WHEEL
Better_PyUnit_Format-0.2.3.dist-info/top_level.txt
Better_PyUnit_Format-0.2.3.dist-info/RECORD
