Metadata-Version: 2.1
Name: Better-PyUnit-Format
Version: 0.2.3
Summary: A more readable text output for Python's built in unittest framework
Author-email: Gregory Bell <trihard.studios@outlook.com>
Project-URL: Repository, https://github.com/gregbell26/BetterPyUnitFormat
Requires-Python: >=3.5
License-File: LICENSE
